GOOD/__init__.py
GOOD/definitions.py
GOOD/data/__init__.py
GOOD/data/dataset_manager.py
GOOD/data/good_datasets/__init__.py
GOOD/data/good_datasets/good_arxiv.py
GOOD/data/good_datasets/good_cbas.py
GOOD/data/good_datasets/good_cmnist.py
GOOD/data/good_datasets/good_cora.py
GOOD/data/good_datasets/good_hiv.py
GOOD/data/good_datasets/good_motif.py
GOOD/data/good_datasets/good_pcba.py
GOOD/data/good_datasets/good_zinc.py
GOOD/data/good_datasets/orig_zinc.py
GOOD/kernel/__init__.py
GOOD/kernel/evaluation.py
GOOD/kernel/pipeline.py
GOOD/kernel/train.py
GOOD/networks/__init__.py
GOOD/networks/model_manager.py
GOOD/networks/models/BaseGNN.py
GOOD/networks/models/Classifiers.py
GOOD/networks/models/CoralGCNs.py
GOOD/networks/models/CoralNN.py
GOOD/networks/models/DANNGCNs.py
GOOD/networks/models/DANNs.py
GOOD/networks/models/GCNs.py
GOOD/networks/models/GINs.py
GOOD/networks/models/GINvirtualnode.py
GOOD/networks/models/MixupGCNs.py
GOOD/networks/models/MixupGNN.py
GOOD/networks/models/MolEncoders.py
GOOD/networks/models/Pooling.py
GOOD/networks/models/__init__.py
GOOD/ood_algorithms/__init__.py
GOOD/ood_algorithms/ood_manager.py
GOOD/ood_algorithms/algorithms/BaseOOD.py
GOOD/ood_algorithms/algorithms/Coral.py
GOOD/ood_algorithms/algorithms/DANN.py
GOOD/ood_algorithms/algorithms/ERM.py
GOOD/ood_algorithms/algorithms/GroupDRO.py
GOOD/ood_algorithms/algorithms/IRM.py
GOOD/ood_algorithms/algorithms/Mixup.py
GOOD/ood_algorithms/algorithms/VREx.py
GOOD/ood_algorithms/algorithms/__init__.py
GOOD/utils/__init__.py
GOOD/utils/args.py
GOOD/utils/config_reader.py
GOOD/utils/data.py
GOOD/utils/graph_visualize.py
GOOD/utils/initial.py
GOOD/utils/logger.py
GOOD/utils/metric.py
GOOD/utils/register.py
GOOD/utils/train.py
GOOD/utils/synthetic_data/BA3_loc.py
GOOD/utils/synthetic_data/__init__.py
GOOD/utils/synthetic_data/featgen.py
GOOD/utils/synthetic_data/synthetic_structsim.py
graph_ood-0.1.0.dist-info/LICENSE
graph_ood-0.1.0.dist-info/METADATA
graph_ood-0.1.0.dist-info/WHEEL
graph_ood-0.1.0.dist-info/entry_points.txt
graph_ood-0.1.0.dist-info/top_level.txt
graph_ood-0.1.0.dist-info/RECORD
