Metadata-Version: 2.1
Name: graph-ood
Version: 0.1.0
Summary: GOOD: A Graph Out-of-Distribution Benchmark
Home-page: https://github.com/divelab/GOOD
Author: Shurui Gui, Xiner Li
Author-email: shurui.gui@tamu.edu
License: GPLv3
Project-URL: Bug Tracker, https://github.com/divelab/GOOD/issues
Classifier: Programming Language :: Python :: 3.8
Classifier: Programming Language :: Python :: 3.9
Classifier: License :: OSI Approved :: GNU General Public License v3 or later (GPLv3+)
Classifier: Operating System :: OS Independent
Requires-Python: >=3.8
License-File: LICENSE
Requires-Dist: cilog (==1.2.3)
Requires-Dist: gdown (==4.4.0)
Requires-Dist: matplotlib (==3.5.2)
Requires-Dist: munch (==2.5.0)
Requires-Dist: networkx (==2.8)
Requires-Dist: ogb (==1.3.3)
Requires-Dist: pytest (==7.1.2)
Requires-Dist: pytest-cov (~=3.0)
Requires-Dist: pytest-xdist (~=2.5)
Requires-Dist: ruamel.yaml (==0.17.21)
Requires-Dist: sphinx (>=4.5)
Requires-Dist: protobuf (==3.20.1)
Requires-Dist: sphinx-rtd-theme (==1.0.0)
Requires-Dist: tensorboard (==2.8.0)
Requires-Dist: tqdm (==4.64.0)
Requires-Dist: typed-argument-parser (==1.7.2)
